advancedcipher/cipher.py
simple_advancedcipherlib-1.0.1.dist-info/METADATA
simple_advancedcipherlib-1.0.1.dist-info/WHEEL
simple_advancedcipherlib-1.0.1.dist-info/top_level.txt
simple_advancedcipherlib-1.0.1.dist-info/RECORD
