Metadata-Version: 2.4
Name: simple_advancedcipherlib
Version: 1.0.1
Summary: Advanced encryption and decryption library with multiple cipher algorithms
Author: Naser Hnysh
Author-email: Naser Hnysh <naserhnysh@gmail.com>
License: MIT
Project-URL: Homepage, https://pypi.org/
Classifier: Programming Language :: Python :: 3
Classifier: License :: OSI Approved :: MIT License
Classifier: Operating System :: OS Independent
Requires-Python: >=3.6
Dynamic: author
Dynamic: requires-python
